scenedetect/__init__.py
scenedetect/__main__.py
scenedetect/bbox_video_stream.py
scenedetect/frame_timecode.py
scenedetect/platform.py
scenedetect/scene_detector.py
scenedetect/scene_manager.py
scenedetect/stats_manager.py
scenedetect/video_manager.py
scenedetect/video_splitter.py
scenedetect/cli/__init__.py
scenedetect/cli/context.py
scenedetect/detectors/__init__.py
scenedetect/detectors/content_detector.py
scenedetect/detectors/motion_detector.py
scenedetect/detectors/threshold_detector.py
scenedetect/thirdparty/LICENCE-PYSCENEDETECT
scenedetect/thirdparty/LICENSE-CLICK
scenedetect/thirdparty/LICENSE-NUMPY
scenedetect/thirdparty/LICENSE-OPENCV
scenedetect/thirdparty/LICENSE-PYTESSERACT
scenedetect/thirdparty/LICENSE-PYTEST
scenedetect/thirdparty/LICENSE-TQDM
scenedetect/thirdparty/LICENSE-TQDM0
scenedetect/thirdparty/__init__.py
scenedetect/thirdparty/simpletable.py
vfxdetect-0.6.3.dist-info/entry_points.txt
vfxdetect-0.6.3.dist-info/LICENSE
vfxdetect-0.6.3.dist-info/WHEEL
vfxdetect-0.6.3.dist-info/METADATA
vfxdetect-0.6.3.dist-info/RECORD
