Metadata-Version: 2.1
Name: vfxdetect
Version: 0.6.3
Summary: A cross-platform, OpenCV-based VFX shot detection program and Python library.
Home-page: https://github.com/ThomasWeckenmann/PyVfxShotDetect
Author: Thomas Weckenmann
Author-email: tweckenmann0711@gmail.com
Classifier: Development Status :: 5 - Production/Stable
Classifier: Environment :: Console
Classifier: Environment :: Console :: Curses
Classifier: Intended Audience :: Developers
Classifier: Intended Audience :: End Users/Desktop
Classifier: Intended Audience :: System Administrators
Classifier: License :: OSI Approved :: MIT License
Classifier: Operating System :: OS Independent
Classifier: Programming Language :: Python :: 3.5
Classifier: Programming Language :: Python :: 3.6
Classifier: Programming Language :: Python :: 3.7
Classifier: Programming Language :: Python :: 3.8
Classifier: Topic :: Multimedia :: Video
Classifier: Topic :: Multimedia :: Video :: Conversion
Classifier: Topic :: Multimedia :: Video :: Non-Linear Editor
Classifier: Topic :: Utilities
Requires-Dist: Click
Requires-Dist: numpy
Requires-Dist: tqdm
Requires-Dist: opencv-python
Requires-Dist: pytesseract
